pymorphy3_dicts_uk/__init__.py
pymorphy3_dicts_uk/version.py
pymorphy3_dicts_uk/data/grammemes.json
pymorphy3_dicts_uk/data/gramtab-opencorpora-ext.json
pymorphy3_dicts_uk/data/gramtab-opencorpora-int.json
pymorphy3_dicts_uk/data/meta.json
pymorphy3_dicts_uk/data/paradigms.array
pymorphy3_dicts_uk/data/prediction-suffixes-0.dawg
pymorphy3_dicts_uk/data/prediction-suffixes-1.dawg
pymorphy3_dicts_uk/data/prediction-suffixes-2.dawg
pymorphy3_dicts_uk/data/prediction-suffixes-3.dawg
pymorphy3_dicts_uk/data/suffixes.json
pymorphy3_dicts_uk/data/words.dawg
pymorphy3_dicts_uk-2.4.1.1.1641732236.dist-info/METADATA
pymorphy3_dicts_uk-2.4.1.1.1641732236.dist-info/WHEEL
pymorphy3_dicts_uk-2.4.1.1.1641732236.dist-info/entry_points.txt
pymorphy3_dicts_uk-2.4.1.1.1641732236.dist-info/top_level.txt
pymorphy3_dicts_uk-2.4.1.1.1641732236.dist-info/RECORD
